weatherly/__init__.py
weatherly/abc.py
weatherly/enums.py
weatherly/errors.py
weatherly/responses.py
weatherly/utils.py
weatherly/api/__init__.py
weatherly/api/client.py
weatherly/api/core.py
weatherly-0.10.0.dist-info/LICENSE
weatherly-0.10.0.dist-info/METADATA
weatherly-0.10.0.dist-info/WHEEL
weatherly-0.10.0.dist-info/top_level.txt
weatherly-0.10.0.dist-info/RECORD
