Metadata-Version: 2.1
Name: weatherly
Version: 0.10.0
Summary: A simple Python wrapper around WeatherAPI. Get current weather, forecast, history and more...
Home-page: https://github.com/konradsic/weatherly
Author: konradsic
License: MIT
Project-URL: Issues, https://github.com/konradsic/weatherly/issues
Classifier: Development Status :: 2 - Pre-Alpha
Classifier: License :: OSI Approved :: MIT License
Classifier: Intended Audience :: Developers
Classifier: Natural Language :: English
Classifier: Operating System :: OS Independent
Classifier: Programming Language :: Python :: 3.10
Classifier: Programming Language :: Python :: 3.11
Classifier: Topic :: Internet
Classifier: Topic :: Software Development :: Libraries
Classifier: Topic :: Software Development :: Libraries :: Python Modules
Classifier: Topic :: Utilities
Classifier: Topic :: Scientific/Engineering :: Atmospheric Science
Classifier: Typing :: Typed
Requires-Python: >=3.10.0
License-File: LICENSE
Requires-Dist: requests (==2.28.2)
Provides-Extra: docs
Requires-Dist: sphinx (==5.3.0) ; extra == 'docs'
Requires-Dist: sphinx-book-theme (==1.0.1) ; extra == 'docs'
Requires-Dist: sphinxcontrib-trio (==1.1.2) ; extra == 'docs'
Requires-Dist: sphinx-copybutton (==0.5.2) ; extra == 'docs'
Provides-Extra: test
Requires-Dist: pytest ; extra == 'test'
Requires-Dist: pytest-cov ; extra == 'test'
